ChangeLog.txt
LICENSE.txt
MANIFEST.in
README.rst
setup.py
dexml2/__init__.py
dexml2/compat.py
dexml2/fields.py
dexml2/test.py
dexml2.egg-info/PKG-INFO
dexml2.egg-info/SOURCES.txt
dexml2.egg-info/dependency_links.txt
dexml2.egg-info/top_level.txt